goat/__init__.py
goat/cmd_preset.py
goat/cmd_slack.py
goat/goat.py
goat/manuals/goat-amazon-cli.1
goat/manuals/goat-amazon-ec2-delete-orphaned_ebs.1
goat/manuals/goat-amazon-ec2-delete.1
goat/manuals/goat-amazon-ec2-refresh.1
goat/manuals/goat-amazon-ec2-show.1
goat/manuals/goat-amazon-ec2.1
goat/manuals/goat-amazon-extract-commands.1
goat/manuals/goat-amazon-extract.1
goat/manuals/goat-amazon-iam-authenticate.1
goat/manuals/goat-amazon-iam.1
goat/manuals/goat-amazon-rds-refresh.1
goat/manuals/goat-amazon-rds-show.1
goat/manuals/goat-amazon-rds.1
goat/manuals/goat-amazon-s3-create.1
goat/manuals/goat-amazon-s3-delete.1
goat/manuals/goat-amazon-s3-download.1
goat/manuals/goat-amazon-s3-refresh.1
goat/manuals/goat-amazon-s3-show.1
goat/manuals/goat-amazon-s3-upload.1
goat/manuals/goat-amazon-s3.1
goat/manuals/goat-amazon-show.1
goat/manuals/goat-amazon.1
goat/manuals/goat-aws-cli.1
goat/manuals/goat-aws-ec2-delete-orphaned_ebs.1
goat/manuals/goat-aws-ec2-delete.1
goat/manuals/goat-aws-ec2-refresh.1
goat/manuals/goat-aws-ec2-show.1
goat/manuals/goat-aws-ec2.1
goat/manuals/goat-aws-extract-commands.1
goat/manuals/goat-aws-extract.1
goat/manuals/goat-aws-iam-authenticate.1
goat/manuals/goat-aws-iam.1
goat/manuals/goat-aws-rds-refresh.1
goat/manuals/goat-aws-rds-show.1
goat/manuals/goat-aws-rds.1
goat/manuals/goat-aws-s3-create.1
goat/manuals/goat-aws-s3-delete.1
goat/manuals/goat-aws-s3-download.1
goat/manuals/goat-aws-s3-refresh.1
goat/manuals/goat-aws-s3-show.1
goat/manuals/goat-aws-s3-upload.1
goat/manuals/goat-aws-s3.1
goat/manuals/goat-aws-show.1
goat/manuals/goat-aws.1
goat/manuals/goat-az-extract-commands.1
goat/manuals/goat-az-extract.1
goat/manuals/goat-az.1
goat/manuals/goat-azdev-auth-config.1
goat/manuals/goat-azdev-auth-setup.1
goat/manuals/goat-azdev-auth.1
goat/manuals/goat-azdev-boards-find.1
goat/manuals/goat-azdev-boards-list.1
goat/manuals/goat-azdev-boards.1
goat/manuals/goat-azdev-config.1
goat/manuals/goat-azdev-issue-search.1
goaat-2024.7.16.1621.dist-info/METADATA
goaat-2024.7.16.1621.dist-info/WHEEL
goaat-2024.7.16.1621.dist-info/entry_points.txt
goaat-2024.7.16.1621.dist-info/top_level.txt
goaat-2024.7.16.1621.dist-info/RECORD
