Metadata-Version: 2.1
Name: goaat
Version: 2024.7.16.1621
Summary: goat => GCP, OCI, & AWS tools : GOAT Team
Author-email: Christopher Stacks <centerupt@gmail.com>
Classifier: Programming Language :: Python :: 3
Classifier: Operating System :: OS Independent
Requires-Python: >=3.7
Requires-Dist: click >=8.0.4
Requires-Dist: importlib-metadata
Requires-Dist: click-man
Requires-Dist: prompt-toolkit >=3
Requires-Dist: goatocitools
Requires-Dist: goatazdevops
Requires-Dist: goataztools
Requires-Dist: goatovhaitools
Requires-Dist: goatibmcloudtools
Requires-Dist: goatawstools
Requires-Dist: goatjiratools
Requires-Dist: goatslacktools
Requires-Dist: goatjenkinstools
Requires-Dist: goatconfigstore
Requires-Dist: goattoolbox
Requires-Dist: goatshell
